README.md
setup.py
py_flood/Target.py
py_flood/__init__.py
py_flood/bro_targets.py
py_flood/flood.py
py_flood.egg-info/PKG-INFO
py_flood.egg-info/SOURCES.txt
py_flood.egg-info/dependency_links.txt
py_flood.egg-info/requires.txt
py_flood.egg-info/top_level.txt