Metadata-Version: 2.1
Name: py-flood
Version: 0.0.2
Summary: udp port flooding, use a cli or just its modules. Integrates with Bro (Zeek) to flood hosts according to their traffic
Home-page: https://github.com/deadlift1226/py_flood
Author: Dane Morgan
Author-email: danemorgan91@gmail.com
License: UNKNOWN
Platform: UNKNOWN
Classifier: Programming Language :: Python :: 3
Classifier: License :: OSI Approved :: MIT License
Classifier: Operating System :: OS Independent
